parstalk/__init__.py
parstalk/core.py
parstalk-1.9.dist-info/licenses/LICENSE
parstalk-1.9.dist-info/METADATA
parstalk-1.9.dist-info/WHEEL
parstalk-1.9.dist-info/top_level.txt
parstalk-1.9.dist-info/RECORD
