Metadata-Version: 2.4
Name: parstalk
Version: 1.9
Summary: تبدیل متن فارسی به فینگلیش با تشخیص مصوت و تبدیل به صدا
Author: Mohammadjavad Ghaderi
Author-email: Mohammadjavadd.ronaldo@gmail.com
Classifier: Programming Language :: Python :: 3
Classifier: Operating System :: OS Independent
License-File: LICENSE
Requires-Dist: pyttsx3
Dynamic: author
Dynamic: author-email
Dynamic: classifier
Dynamic: license-file
Dynamic: requires-dist
Dynamic: summary
